odoo/addons/account_invoice_check_picking_date/README.rst
odoo/addons/account_invoice_check_picking_date/__init__.py
odoo/addons/account_invoice_check_picking_date/__manifest__.py
odoo/addons/account_invoice_check_picking_date/i18n/account_invoice_check_picking_date.pot
odoo/addons/account_invoice_check_picking_date/i18n/es.po
odoo/addons/account_invoice_check_picking_date/i18n/it.po
odoo/addons/account_invoice_check_picking_date/models/__init__.py
odoo/addons/account_invoice_check_picking_date/models/account_move.py
odoo/addons/account_invoice_check_picking_date/readme/CONTRIBUTORS.rst
odoo/addons/account_invoice_check_picking_date/readme/DESCRIPTION.rst
odoo/addons/account_invoice_check_picking_date/readme/INSTALL.rst
odoo/addons/account_invoice_check_picking_date/readme/USAGE.rst
odoo/addons/account_invoice_check_picking_date/security/ir.model.access.csv
odoo/addons/account_invoice_check_picking_date/static/description/icon.png
odoo/addons/account_invoice_check_picking_date/static/description/index.html
odoo/addons/account_invoice_check_picking_date/tests/__init__.py
odoo/addons/account_invoice_check_picking_date/tests/test_account_invoice_check_picking_date.py
odoo/addons/account_invoice_check_picking_date/wizards/__init__.py
odoo/addons/account_invoice_check_picking_date/wizards/invoice_stock_picking_date_wiz.py
odoo/addons/account_invoice_check_picking_date/wizards/invoice_stock_picking_date_wiz.xml
odoo_addon_account_invoice_check_picking_date-16.0.1.0.1.2.dist-info/METADATA
odoo_addon_account_invoice_check_picking_date-16.0.1.0.1.2.dist-info/WHEEL
odoo_addon_account_invoice_check_picking_date-16.0.1.0.1.2.dist-info/top_level.txt
odoo_addon_account_invoice_check_picking_date-16.0.1.0.1.2.dist-info/RECORD
