Metadata-Version: 2.1
Name: odoo-addon-account_invoice_check_picking_date
Version: 16.0.1.0.1.2
Summary: Check if date of pickings match with accounting date
Home-page: https://github.com/OCA/account-invoicing
Author: Tecnativa, Odoo Community Association (OCA)
Author-email: support@odoo-community.org
License: AGPL-3
Classifier: Programming Language :: Python
Classifier: Framework :: Odoo
Classifier: Framework :: Odoo :: 16.0
Classifier: License :: OSI Approved :: GNU Affero General Public License v3
Classifier: Development Status :: 5 - Production/Stable
Requires-Python: >=3.10
Requires-Dist: odoo<16.1dev,>=16.0a
